omegaconf_cloud_resolvers/__init__.py
omegaconf_cloud_resolvers/resolvers/__init__.py
omegaconf_cloud_resolvers/resolvers/aux.py
omegaconf_cloud_resolvers/resolvers/aws/__init__.py
omegaconf_cloud_resolvers/resolvers/aws/base.py
omegaconf_cloud_resolvers/resolvers/aws/parameterstore.py
omegaconf_cloud_resolvers/resolvers/aws/secretsmanager.py
omegaconf_cloud_resolvers/resolvers/az/__init__.py
omegaconf_cloud_resolvers/resolvers/az/base.py
omegaconf_cloud_resolvers/resolvers/az/keyvault.py
omegaconf_cloud_resolvers/resolvers/base.py
omegaconf_cloud_resolvers/resolvers/gcp/__init__.py
omegaconf_cloud_resolvers/resolvers/gcp/base.py
omegaconf_cloud_resolvers/resolvers/gcp/secretmanager.py
omegaconf_cloud_resolvers-0.2.0.dist-info/LICENSE
omegaconf_cloud_resolvers-0.2.0.dist-info/METADATA
omegaconf_cloud_resolvers-0.2.0.dist-info/WHEEL
omegaconf_cloud_resolvers-0.2.0.dist-info/RECORD
