Metadata-Version: 2.1
Name: omegaconf-cloud-resolvers
Version: 0.2.0
Summary: Omegaconf custom resolvers to retrieve configuration values from cloud services
Author: M Gil Valverde
Author-email: m.gilvalverde@gmail.com
Requires-Python: >=3.9,<4.0
Classifier: Programming Language :: Python :: 3
Classifier: Programming Language :: Python :: 3.9
Classifier: Programming Language :: Python :: 3.10
Classifier: Programming Language :: Python :: 3.11
Classifier: Programming Language :: Python :: 3.12
Provides-Extra: aws
Provides-Extra: az
Provides-Extra: gcp
Requires-Dist: azure-identity (>=1.18.0,<2.0.0) ; extra == "az"
Requires-Dist: azure-keyvault-secrets (>=4.8.0,<5.0.0) ; extra == "az"
Requires-Dist: boto3 (>=1.34.16,<2.0.0) ; extra == "aws"
Requires-Dist: google-cloud-secret-manager (>=2.20.2,<3.0.0) ; extra == "gcp"
Requires-Dist: jmespath (>=1.0.1,<2.0.0)
Requires-Dist: omegaconf (>=2.3.0,<3.0.0)
